README.md
dedoop.py
setup.cfg
setup.py
dedoop.egg-info/PKG-INFO
dedoop.egg-info/SOURCES.txt
dedoop.egg-info/dependency_links.txt
dedoop.egg-info/entry_points.txt
dedoop.egg-info/requires.txt
dedoop.egg-info/top_level.txt