Metadata-Version: 2.1
Name: dedoop
Version: 0.0.4
Summary: dedupe files and send them to the cloud
Home-page: https://github.com/edsu/dedoop
Author: Ed Summers
Author-email: ehs@pobox.com
License: UNKNOWN
Platform: UNKNOWN
